memberful/__init__.py
memberful/api/__init__.py
memberful/api/models.py
memberful/webhooks/__init__.py
memberful/webhooks/models.py
memberful-0.1.0.dist-info/METADATA
memberful-0.1.0.dist-info/WHEEL
memberful-0.1.0.dist-info/licenses/LICENSE
memberful-0.1.0.dist-info/RECORD
