Metadata-Version: 2.4
Name: memberful
Version: 0.1.0
Summary: Memberful service Python client for webhooks and API
Project-URL: Homepage, https://github.com/mikeckennedy/memberful
Project-URL: Repository, https://github.com/mikeckennedy/memberful.git
Project-URL: Issues, https://github.com/mikeckennedy/memberful/issues
Project-URL: Changelog, https://github.com/mikeckennedy/memberful/blob/main/CHANGELOG.md
Author: Michael Kennedy
Maintainer: Michael Kennedy
License: MIT License
License-File: LICENSE
Keywords: api,memberful,membership,subscription,webhooks
Classifier: Development Status :: 3 - Alpha
Classifier: Intended Audience :: Developers
Classifier: License :: OSI Approved :: MIT License
Classifier: Operating System :: OS Independent
Classifier: Programming Language :: Python :: 3
Classifier: Programming Language :: Python :: 3.10
Classifier: Programming Language :: Python :: 3.11
Classifier: Programming Language :: Python :: 3.12
Classifier: Programming Language :: Python :: 3.13
Classifier: Topic :: Internet :: WWW/HTTP
Classifier: Topic :: Software Development :: Libraries :: Python Modules
Requires-Python: >=3.10
Requires-Dist: httpx>=0.25.0
Requires-Dist: pydantic>=2.0.0
Requires-Dist: stamina>=24.0.0
Provides-Extra: dev
Requires-Dist: mypy>=1.7.0; extra == 'dev'
Requires-Dist: pre-commit>=3.0.0; extra == 'dev'
Requires-Dist: pytest-asyncio>=0.21.0; extra == 'dev'
Requires-Dist: pytest-cov>=4.0.0; extra == 'dev'
Requires-Dist: pytest>=7.0.0; extra == 'dev'
Requires-Dist: ruff>=0.1.0; extra == 'dev'
